README.md
setup.py
PlotDot.egg-info/PKG-INFO
PlotDot.egg-info/SOURCES.txt
PlotDot.egg-info/dependency_links.txt
PlotDot.egg-info/requires.txt
PlotDot.egg-info/top_level.txt
plotdot/__init__.py
plotdot/rdkit.py