Metadata-Version: 2.1
Name: PlotDot
Version: 0.0.5
Summary: Utility for plotting perceputally uniform dots.
Home-page: https://github.com/swamidasslab/plotdot/
Author: S. Joshua Swamidass
Author-email: swamidass@wustl.edu
License: UNKNOWN
Platform: UNKNOWN
